Workbook

Sheet Transactions
A1: Order_ID | B1: Order_Date | C1: Customer_Raw | D1: Region | E1: Product_ID | F1: Units | G1: Unit_Price | H1: Sales | I1: Payment_Method | J1: Channel | K1: Order_Status | L1: Product_VLOOKUP | M1: Unit_Price_XLOOKUP | N1: Category_XLOOKUP | O1: Customer_Clean | P1: Sales_Band_IF | Q1: Order_Flag_IF
A2: RT0001 | B2: 46085 | C2: Priya Nair | D2: South | E2: P102 | F2: 1 | G2: 2499 | H2: 2499 | I2: Card | J2: Online | K2: Cancelled | L2: =VLOOKUP(E2,Lookup_Data!$A$2:$D$11,2,FALSE) | M2: =XLOOKUP(E2,Lookup_Data!$A$2:$A$11,Lookup_Data!$D$2:$D$11,"Not Found") | N2: =XLOOKUP(E2,Lookup_Data!$A$2:$A$11,Lookup_Data!$C$2:$C$11,"Not Found") | O2: =PROPER(TRIM(C2)) | P2: =IF(H2>=20000,"High Value",IF(H2>=10000,"Medium Value","Standard")) | Q2: =IF(K2="Completed","Include","Review")
A3: RT0002 | B3: 46131 | C3: Aman Gupta | D3: North | E3: P109 | F3: 1 | G3: 6999 | H3: 6999 | I3: UPI | J3: Online | K3: Completed | L3: =VLOOKUP(E3,Lookup_Data!$A$2:$D$11,2,FALSE) | M3: =XLOOKUP(E3,Lookup_Data!$A$2:$A$11,Lookup_Data!$D$2:$D$11,"Not Found") | N3: =XLOOKUP(E3,Lookup_Data!$A$2:$A$11,Lookup_Data!$C$2:$C$11,"Not Found") | O3: =PROPER(TRIM(C3)) | P3: =IF(H3>=20000,"High Value",IF(H3>=10000,"Medium Value","Standard")) | Q3: =IF(K3="Completed","Include","Review")
A4: RT0003 | B4: 46029 | C4: Aman Gupta | D4: South | E4: P104 | F4: 5 | G4: 18999 | H4: 94995 | I4: Cash | J4: Online | K4: Completed | L4: =VLOOKUP(E4,Lookup_Data!$A$2:$D$11,2,FALSE) | M4: =XLOOKUP(E4,Lookup_Data!$A$2:$A$11,Lookup_Data!$D$2:$D$11,"Not Found") | N4: =XLOOKUP(E4,Lookup_Data!$A$2:$A$11,Lookup_Data!$C$2:$C$11,"Not Found") | O4: =PROPER(TRIM(C4)) | P4: =IF(H4>=20000,"High Value",IF(H4>=10000,"Medium Value","Standard")) | Q4: =IF(K4="Completed","Include","Review")
A5: RT0004 | B5: 46063 | C5: anita sharma | D5: West | E5: P110 | F5: 3 | G5: 5899 | H5: 17697 | I5: Net Banking | J5: Store | K5: Completed | L5: =VLOOKUP(E5,Lookup_Data!$A$2:$D$11,2,FALSE) | M5: =XLOOKUP(E5,Lookup_Data!$A$2:$A$11,Lookup_Data!$D$2:$D$11,"Not Found") | N5: =XLOOKUP(E5,Lookup_Data!$A$2:$A$11,Lookup_Data!$C$2:$C$11,"Not Found") | O5: =PROPER(TRIM(C5)) | P5: =IF(H5>=20000,"High Value",IF(H5>=10000,"Medium Value","Standard")) | Q5: =IF(K5="Completed","Include","Review")
A6: RT0005 | B6: 46046 | C6: Rohit Mehta | D6: West | E6: P104 | F6: 3 | G6: 18999 | H6: 56997 | I6: UPI | J6: Store | K6: Completed | L6: =VLOOKUP(E6,Lookup_Data!$A$2:$D$11,2,FALSE) | M6: =XLOOKUP(E6,Lookup_Data!$A$2:$A$11,Lookup_Data!$D$2:$D$11,"Not Found") | N6: =XLOOKUP(E6,Lookup_Data!$A$2:$A$11,Lookup_Data!$C$2:$C$11,"Not Found") | O6: =PROPER(TRIM(C6)) | P6: =IF(H6>=20000,"High Value",IF(H6>=10000,"Medium Value","Standard")) | Q6: =IF(K6="Completed","Include","Review")
A7: RT0006 | B7: 46140 | C7: anita sharma | D7: North | E7: P110 | F7: 3 | G7: 5899 | H7: 17697 | I7: Cash | J7: Online | K7: Pending | L7: =VLOOKUP(E7,Lookup_Data!$A$2:$D$11,2,FALSE) | M7: =XLOOKUP(E7,Lookup_Data!$A$2:$A$11,Lookup_Data!$D$2:$D$11,"Not Found") | N7: =XLOOKUP(E7,Lookup_Data!$A$2:$A$11,Lookup_Data!$C$2:$C$11,"Not Found") | O7: =PROPER(TRIM(C7)) | P7: =IF(H7>=20000,"High Value",IF(H7>=10000,"Medium Value","Standard")) | Q7: =IF(K7="Completed","Include","Review")
A8: RT0007 | B8: 46170 | C8: Arjun Patel | D8: South | E8: P105 | F8: 5 | G8: 1299 | H8: 6495 | I8: UPI | J8: Online | K8: Cancelled | L8: =VLOOKUP(E8,Lookup_Data!$A$2:$D$11,2,FALSE) | M8: =XLOOKUP(E8,Lookup_Data!$A$2:$A$11,Lookup_Data!$D$2:$D$11,"Not Found") | N8: =XLOOKUP(E8,Lookup_Data!$A$2:$A$11,Lookup_Data!$C$2:$C$11,"Not Found") | O8: =PROPER(TRIM(C8)) | P8: =IF(H8>=20000,"High Value",IF(H8>=10000,"Medium Value","Standard")) | Q8: =IF(K8="Completed","Include","Review")
A9: RT0008 | B9: 46082 | C9: Rohit Mehta | D9: North | E9: P104 | F9: 3 | G9: 18999 | H9: 56997 | I9: Cash | J9: Store | K9: Completed | L9: =VLOOKUP(E9,Lookup_Data!$A$2:$D$11,2,FALSE) | M9: =XLOOKUP(E9,Lookup_Data!$A$2:$A$11,Lookup_Data!$D$2:$D$11,"Not Found") | N9: =XLOOKUP(E9,Lookup_Data!$A$2:$A$11,Lookup_Data!$C$2:$C$11,"Not Found") | O9: =PROPER(TRIM(C9)) | P9: =IF(H9>=20000,"High Value",IF(H9>=10000,"Medium Value","Standard")) | Q9: =IF(K9="Completed","Include","Review")
A10: RT0009 | B10: 46113 | C10: Arjun Patel | D10: South | E10: P106 | F10: 2 | G10: 3499 | H10: 6998 | I10: Net Banking | J10: Online | K10: Pending | L10: =VLOOKUP(E10,Lookup_Data!$A$2:$D$11,2,FALSE) | M10: =XLOOKUP(E10,Lookup_Data!$A$2:$A$11,Lookup_Data!$D$2:$D$11,"Not Found") | N10: =XLOOKUP(E10,Lookup_Data!$A$2:$A$11,Lookup_Data!$C$2:$C$11,"Not Found") | O10: =PROPER(TRIM(C10)) | P10: =IF(H10>=20000,"High Value",IF(H10>=10000,"Medium Value","Standard")) | Q10: =IF(K10="Completed","Include","Review")
A11: RT0010 | B11: 46064 | C11: Vivek Singh | D11: West | E11: P103 | F11: 5 | G11: 1599 | H11: 7995 | I11: Cash | J11: Store | K11: Cancelled | L11: =VLOOKUP(E11,Lookup_Data!$A$2:$D$11,2,FALSE) | M11: =XLOOKUP(E11,Lookup_Data!$A$2:$A$11,Lookup_Data!$D$2:$D$11,"Not Found") | N11: =XLOOKUP(E11,Lookup_Data!$A$2:$A$11,Lookup_Data!$C$2:$C$11,"Not Found") | O11: =PROPER(TRIM(C11)) | P11: =IF(H11>=20000,"High Value",IF(H11>=10000,"Medium Value","Standard")) | Q11: =IF(K11="Completed","Include","Review")
A12: RT0011 | B12: 46037 | C12: Arjun Patel | D12: South | E12: P109 | F12: 2 | G12: 6999 | H12: 13998 | I12: UPI | J12: Store | K12: Completed | L12: =VLOOKUP(E12,Lookup_Data!$A$2:$D$11,2,FALSE) | M12: =XLOOKUP(E12,Lookup_Data!$A$2:$A$11,Lookup_Data!$D$2:$D$11,"Not Found") | N12: =XLOOKUP(E12,Lookup_Data!$A$2:$A$11,Lookup_Data!$C$2:$C$11,"Not Found") | O12: =PROPER(TRIM(C12)) | P12: =IF(H12>=20000,"High Value",IF(H12>=10000,"Medium Value","Standard")) | Q12: =IF(K12="Completed","Include","Review")
A13: RT0012 | B13: 46168 | C13: Vivek Singh | D13: East | E13: P105 | F13: 1 | G13: 1299 | H13: 1299 | I13: Card | J13: Store | K13: Completed | L13: =VLOOKUP(E13,Lookup_Data!$A$2:$D$11,2,FALSE) | M13: =XLOOKUP(E13,Lookup_Data!$A$2:$A$11,Lookup_Data!$D$2:$D$11,"Not Found") | N13: =XLOOKUP(E13,Lookup_Data!$A$2:$A$11,Lookup_Data!$C$2:$C$11,"Not Found") | O13: =PROPER(TRIM(C13)) | P13: =IF(H13>=20000,"High Value",IF(H13>=10000,"Medium Value","Standard")) | Q13: =IF(K13="Completed","Include","Review")
... A61: RT0060 | B61: 46066 | C61: Sanjay Verma | D61: North | E61: P104 | F61: 5 | G61: 18999 | H61: 94995 | I61: Net Banking | J61: Store | K61: Completed | L61: =VLOOKUP(E61,Lookup_Data!$A$2:$D$11,2,FALSE) | M61: =XLOOKUP(E61,Lookup_Data!$A$2:$A$11,Lookup_Data!$D$2:$D$11,"Not Found") | N61: =XLOOKUP(E61,Lookup_Data!$A$2:$A$11,Lookup_Data!$C$2:$C$11,"Not Found") | O61: =PROPER(TRIM(C61)) | P61: =IF(H61>=20000,"High Value",IF(H61>=10000,"Medium Value","Standard")) | Q61: =IF(K61="Completed","Include","Review")

Sheet Lookup_Data
A1: Product_ID | B1: Product_Name | C1: Category | D1: Unit_Price
A2: P101 | B2: Wireless Mouse | C2: Accessories | D2: 799
A3: P102 | B3: Mechanical Keyboard | C3: Accessories | D3: 2499
A4: P103 | B4: USB-C Hub | C4: Accessories | D4: 1599
A5: P104 | B5: 27-inch Monitor | C5: Monitors | D5: 18999
A6: P105 | B6: Laptop Stand | C6: Accessories | D6: 1299
A7: P106 | B7: Bluetooth Speaker | C7: Audio | D7: 3499
A8: P107 | B8: Noise Cancelling Headphones | C8: Audio | D8: 7999
A9: P108 | B9: Webcam | C9: Accessories | D9: 4299
A10: P109 | B10: SSD 1TB | C10: Storage | D10: 6999
A11: P110 | B11: External HDD 2TB | C11: Storage | D11: 5899

Sheet Analysis
A1: Retail Sales Formula Analysis
A3: Metric | B3: Formula / Result | G3: Formula | H3: Purpose
A4: Completed Sales | B4: =SUMIFS(Transactions!$H:$H,Transactions!$K:$K,"Completed") | G4: VLOOKUP | H4: Find product name from Product_ID using a left-to-right lookup.
A5: Completed Orders | B5: =COUNTIFS(Transactions!$K:$K,"Completed") | G5: XLOOKUP | H5: Return price/category from Product_ID; easier and more flexible than VLOOKUP.
A6: Average Completed Order | B6: =B4/B5 | G6: IF | H6: Classify orders into value bands and operational flags.
A7: High-Value Completed Orders | B7: =COUNTIFS(Transactions!$K:$K,"Completed",Transactions!$H:$H,">=20000") | G7: SUMIFS | H7: Sum completed sales using one or more criteria.
G8: COUNTIFS | H8: Count completed/high-value orders using multiple criteria.
G9: TRIM + PROPER | H9: Clean extra spaces and standardize customer names.
A10: Sales by Region | D10: Sales by Category | G10: LEFT / RIGHT | H10: Extract prefixes/suffixes from IDs or text when needed.
A11: Region | B11: Completed Sales | D11: Category | E11: Completed Sales
A12: North | B12: =SUMIFS(Transactions!$H:$H,Transactions!$D:$D,A12,Transactions!$K:$K,"Completed") | D12: Accessories | E12: =SUMIFS(Transactions!$H:$H,Transactions!$N:$N,D12,Transactions!$K:$K,"Completed")
A13: South | B13: =SUMIFS(Transactions!$H:$H,Transactions!$D:$D,A13,Transactions!$K:$K,"Completed") | D13: Monitors | E13: =SUMIFS(Transactions!$H:$H,Transactions!$N:$N,D13,Transactions!$K:$K,"Completed")
A14: East | B14: =SUMIFS(Transactions!$H:$H,Transactions!$D:$D,A14,Transactions!$K:$K,"Completed") | D14: Audio | E14: =SUMIFS(Transactions!$H:$H,Transactions!$N:$N,D14,Transactions!$K:$K,"Completed")
A15: West | B15: =SUMIFS(Transactions!$H:$H,Transactions!$D:$D,A15,Transactions!$K:$K,"Completed") | D15: Storage | E15: =SUMIFS(Transactions!$H:$H,Transactions!$N:$N,D15,Transactions!$K:$K,"Completed")

Sheet Formula_Guide
A1: Function | B1: Example Formula | C1: When to Use
A2: VLOOKUP | B2: =VLOOKUP(E2,Lookup_Data!$A$2:$D$11,2,FALSE) | C2: Legacy-friendly lookup when key is in the first column.
A3: XLOOKUP | B3: =XLOOKUP(E2,Lookup_Data!$A$2:$A$11,Lookup_Data!$D$2:$D$11,"Not Found") | C3: Preferred modern lookup; supports exact match and flexible return columns.
A4: IF | B4: =IF(H2>=20000,"High Value","Standard") | C4: Create business rules or categories.
A5: SUMIFS | B5: =SUMIFS(Transactions!$H:$H,Transactions!$K:$K,"Completed") | C5: Aggregate a numeric field with multiple conditions.
A6: COUNTIFS | B6: =COUNTIFS(Transactions!$K:$K,"Completed",Transactions!$H:$H,">=20000") | C6: Count records meeting multiple conditions.
A7: TRIM | B7: =TRIM(C2) | C7: Remove leading, trailing and repeated spaces.
A8: PROPER | B8: =PROPER(TRIM(C2)) | C8: Standardize names and labels.
A9: LEFT | B9: =LEFT(A2,2) | C9: Extract the first characters from an ID/text value.
A10: RIGHT | B10: =RIGHT(A2,4) | C10: Extract the last characters from an ID/text value.

Sheet README
A1: Project | B1: Excel Formulas & Functions Fundamentals – Solution 1
A2: Dataset | B2: Electronics Retail Transactions (synthetic practice dataset)
A3: Functions Demonstrated | B3: VLOOKUP, XLOOKUP, IF, SUMIFS, COUNTIFS, TRIM, PROPER, LEFT, RIGHT
A4: How to Use | B4: Open Transactions to see formulas on live rows; Lookup_Data contains the reference table; Analysis contains KPI formulas.
A5: Edge Cases | B5: Product IDs are exact-match lookups; customer names contain extra spaces; cancelled/pending orders are separated from completed sales.
A6: Expected Outcome | B6: A practical workbook showing how core Excel functions support everyday analyst work.
